power_calculator_zimjing/__init__.py
power_calculator_zimjing/example.py
power_calculator_zimjing/mcp_server.py
power_calculator_zimjing-0.2.0.dist-info/METADATA
power_calculator_zimjing-0.2.0.dist-info/WHEEL
power_calculator_zimjing-0.2.0.dist-info/licenses/LICENSE
power_calculator_zimjing-0.2.0.dist-info/RECORD
