Metadata-Version: 2.4
Name: power_calculator_zimjing
Version: 0.2.0
Summary: 一个提供乘方计算服务的MCP服务器包
Project-URL: Homepage, https://github.com/zimjing/power_calculator
Project-URL: Bug Tracker, https://github.com/zimjing/power_calculator/issues
Author-email: Zim Jing <340552684@qq.com>
License-File: LICENSE
Classifier: License :: OSI Approved :: MIT License
Classifier: Operating System :: OS Independent
Classifier: Programming Language :: Python :: 3
Requires-Python: >=3.7
